pandas-sharkbite/__init__.py
pandas-sharkbite/pandassharkbite.py
pandas-sharkbite/torch.py
pandashark/__init__.py
pandashark/pandassharkbite.py
pandashark/torch.py
pandashark-1.1.1.1.dist-info/LICENSE
pandashark-1.1.1.1.dist-info/METADATA
pandashark-1.1.1.1.dist-info/WHEEL
pandashark-1.1.1.1.dist-info/top_level.txt
pandashark-1.1.1.1.dist-info/RECORD
